hayde/__init__.py
hayde/cli.py
hayde/config.py
hayde/inputs.py
hayde/outputs.py
hayde-0.1.2.dist-info/entry_points.txt
hayde-0.1.2.dist-info/LICENSE
hayde-0.1.2.dist-info/WHEEL
hayde-0.1.2.dist-info/METADATA
hayde-0.1.2.dist-info/RECORD
